albatross_sdk/__init__.py
albatross_sdk/lib.py
albatross_sdk-0.1.3.dist-info/METADATA
albatross_sdk-0.1.3.dist-info/WHEEL
albatross_sdk-0.1.3.dist-info/top_level.txt
albatross_sdk-0.1.3.dist-info/RECORD
