Metadata-Version: 2.1
Name: albatross-sdk
Version: 0.1.3
Summary: Python SDK for interacting with the Albatross API
Home-page: https://github.com/albatross-core/py-sdk
Author: Albatross
Author-email: developers@usealbatross.ai
Project-URL: Bug Tracker, https://github.com/albatross-core/py-sdk/issues
Classifier: Development Status :: 4 - Beta
Classifier: Intended Audience :: Developers
Classifier: License :: OSI Approved :: MIT License
Classifier: Operating System :: OS Independent
Classifier: Programming Language :: Python :: 3
Classifier: Programming Language :: Python :: 3.12
Classifier: Topic :: Software Development :: Libraries :: Python Modules
Requires-Python: >=3.12
Requires-Dist: requests >=2.31.0
Requires-Dist: cryptography >=42.0.0
Requires-Dist: python-jose >=3.3.0
Provides-Extra: dev
Requires-Dist: pytest >=7.0.0 ; extra == 'dev'
Requires-Dist: responses >=0.24.0 ; extra == 'dev'
Requires-Dist: pyright >=1.1.0 ; extra == 'dev'
